simon_library/__init__.py
simon_library/class_feature_processing.py
simon_library/class_get_data.py
simon_library/class_prerpocess_data.py
simon_library/class_train_model.py
simon_library/clean_data.py
simon_library/create_features.py
simon_library/get_data.py
simon_library/get_roc_auc.py
simon_library/split_data.py
simon_library/train_model.py
simon_library-0.7.0.dist-info/LICENSE
simon_library-0.7.0.dist-info/METADATA
simon_library-0.7.0.dist-info/WHEEL
simon_library-0.7.0.dist-info/top_level.txt
simon_library-0.7.0.dist-info/RECORD
